examples/__init__.py
examples/http_api.py
protobuf_cloud_datastore_translator/__init__.py
protobuf_cloud_datastore_translator/py.typed
protobuf_cloud_datastore_translator/translator.py
protobuf_cloud_datastore_translator/utils.py
tests/generated/__init__.py
tests/generated/example2_pb2.py
tests/generated/example_pb2.py
tests/generated/example_with_options_pb2.py
tests/generated/options_pb2.py
tests/generated/compat/__init__.py
tests/generated/compat/example_compat_pb2.py
tests/generated/models/__init__.py
tests/generated/models/example3_pb2.py
tests/generated/models/example_with_options_pb2.py
tests/generated/models/options_pb2.py
tests/integration/__init__.py
tests/integration/base.py
tests/integration/test_cross_lang_compatibility.py
tests/integration/test_translator.py
tests/unit/__init__.py
tests/unit/test_translator.py
tests/unit/test_utils.py
protobuf_cloud_datastore_translator-0.1.13.dist-info/LICENSE
protobuf_cloud_datastore_translator-0.1.13.dist-info/METADATA
protobuf_cloud_datastore_translator-0.1.13.dist-info/WHEEL
protobuf_cloud_datastore_translator-0.1.13.dist-info/top_level.txt
protobuf_cloud_datastore_translator-0.1.13.dist-info/RECORD
