Metadata-Version: 2.1
Name: protobuf-cloud-datastore-translator
Version: 0.1.13
Summary: Library which converts arbitrary Protobuf message objects into Entity Protobuf objects which can be used with Google Datastore.
Home-page: UNKNOWN
Author: Tomaz Muraus
Author-email: tomaz@tomaz.me
License: Apache License (2.0)
Platform: UNKNOWN
Classifier: Intended Audience :: Information Technology
Classifier: Operating System :: POSIX :: Linux
Classifier: Programming Language :: Python
Classifier: Programming Language :: Python :: 2.7
Classifier: Programming Language :: Python :: 3
Classifier: Programming Language :: Python :: 3.6
Classifier: Programming Language :: Python :: 3.7
Requires-Dist: six
Requires-Dist: protobuf
Requires-Dist: google-cloud-datastore
